numgraph/__init__.py
numgraph/distributions/__init__.py
numgraph/distributions/_barabasi_albert.py
numgraph/distributions/_clique.py
numgraph/distributions/_erdos_renyi.py
numgraph/distributions/_grid.py
numgraph/distributions/_random_tree.py
numgraph/distributions/_sbm.py
numgraph/distributions/_star.py
numgraph/temporal/__init__.py
numgraph/temporal/_euler_diffusion.py
numgraph/temporal/_heat_diffusion.py
numgraph/temporal/_susceptible_infected.py
numgraph/utils/__init__.py
numgraph/utils/_utils.py
numgraph/utils/spikes_generator.py
numgraph-0.1.8.dist-info/LICENSE
numgraph-0.1.8.dist-info/METADATA
numgraph-0.1.8.dist-info/WHEEL
numgraph-0.1.8.dist-info/top_level.txt
numgraph-0.1.8.dist-info/RECORD
