Metadata-Version: 2.1
Name: numgraph
Version: 0.1.8
Summary: Utility package for generating graph structures
Home-page: https://github.com/gravins/NumGraph
Author: Alessio Gravina, Danilo Numeroso
Author-email: alessio.gravina@phd.unipi.it, danilo.numeroso@phd.unipi.it
Project-URL: Bug Tracker, https://github.com/gravins/NumGraph
Classifier: Programming Language :: Python :: 3
Classifier: License :: OSI Approved :: MIT License
Classifier: Operating System :: OS Independent
Requires-Python: >=3.8
License-File: LICENSE
Requires-Dist: numpy >=1.21
